{
  "name": "nimly",
  "url": "https://github.com/loloicci/nimly",
  "method": "git",
  "tags": [
    "lexer",
    "parser",
    "lexer-generator",
    "parser-generator",
    "lex",
    "yacc",
    "BNF",
    "EBNF"
  ],
  "description": "Lexer Generator and Parser Generator as a Macro Library in Nim.",
  "license": "MIT",
  "web": "https://github.com/loloicci/nimly",
  "refs": {
    "HEAD": {
      "name": "nimly",
      "version": "0.7.0",
      "author": "loloicci",
      "desc": "Lexer Generator and Parser Generator as a library in Nim.",
      "license": "MIT",
      "skipDirs": [],
      "skipFiles": [],
      "skipExt": [],
      "installDirs": [],
      "installFiles": [],
      "installExt": [],
      "requires": [
        {
          "name": "nim",
          "str": ">= 1.4.0",
          "ver": {
            "kind": "verEqLater",
            "ver": "1.4.0"
          }
        },
        {
          "name": "patty",
          "str": ">= 0.3.3",
          "ver": {
            "kind": "verEqLater",
            "ver": "0.3.3"
          }
        }
      ],
      "bin": [],
      "binDir": "",
      "srcDir": "src",
      "backend": "c",
      "ref": "HEAD",
      "rev": "952f083b76e42288326173bc8c50e4b845dad04b"
    },
    "refs/heads/master": {
      "name": "nimly",
      "version": "0.7.0",
      "author": "loloicci",
      "desc": "Lexer Generator and Parser Generator as a library in Nim.",
      "license": "MIT",
      "skipDirs": [],
      "skipFiles": [],
      "skipExt": [],
      "installDirs": [],
      "installFiles": [],
      "installExt": [],
      "requires": [
        {
          "name": "nim",
          "str": ">= 1.4.0",
          "ver": {
            "kind": "verEqLater",
            "ver": "1.4.0"
          }
        },
        {
          "name": "patty",
          "str": ">= 0.3.3",
          "ver": {
            "kind": "verEqLater",
            "ver": "0.3.3"
          }
        }
      ],
      "bin": [],
      "binDir": "",
      "srcDir": "src",
      "backend": "c",
      "ref": "refs/heads/master",
      "rev": "952f083b76e42288326173bc8c50e4b845dad04b"
    },
    "refs/heads/use-quote": {
      "name": "nimly",
      "version": "0.5.1",
      "author": "Lolo Iccl",
      "desc": "Lexer Generator and Parser Generator as a library in Nim.",
      "license": "GPL-3.0",
      "skipDirs": [],
      "skipFiles": [],
      "skipExt": [],
      "installDirs": [],
      "installFiles": [],
      "installExt": [],
      "requires": [
        {
          "name": "nim",
          "str": ">= 1.0.0",
          "ver": {
            "kind": "verEqLater",
            "ver": "1.0.0"
          }
        },
        {
          "name": "patty",
          "str": ">= 0.3.3",
          "ver": {
            "kind": "verEqLater",
            "ver": "0.3.3"
          }
        }
      ],
      "bin": [],
      "binDir": "",
      "srcDir": "src",
      "backend": "c",
      "ref": "refs/heads/use-quote",
      "rev": "13b171ed1009859615c574250e9f7ec907a5aa5b"
    },
    "refs/tags/v0.0.0": {
      "name": "nimly",
      "version": "0.0.0",
      "author": "Lolo Iccl",
      "desc": "A lexer generator and parser generator package work in Nim.",
      "license": "GPL-3.0",
      "skipDirs": [],
      "skipFiles": [],
      "skipExt": [],
      "installDirs": [],
      "installFiles": [],
      "installExt": [],
      "requires": [
        {
          "name": "nim",
          "str": ">= 0.19.4",
          "ver": {
            "kind": "verEqLater",
            "ver": "0.19.4"
          }
        },
        {
          "name": "patty",
          "str": ">= 0.3.3",
          "ver": {
            "kind": "verEqLater",
            "ver": "0.3.3"
          }
        }
      ],
      "bin": [],
      "binDir": "",
      "srcDir": "src",
      "backend": "c",
      "ref": "refs/tags/v0.0.0",
      "rev": "9d8389be345cd9de26f16950a5ddfb32d03df32b"
    },
    "refs/tags/v0.1.0": {
      "name": "nimly",
      "version": "0.1.0",
      "author": "Lolo Iccl",
      "desc": "A lexer generator and parser generator package work in Nim.",
      "license": "GPL-3.0",
      "skipDirs": [],
      "skipFiles": [],
      "skipExt": [],
      "installDirs": [],
      "installFiles": [],
      "installExt": [],
      "requires": [
        {
          "name": "nim",
          "str": ">= 0.19.4",
          "ver": {
            "kind": "verEqLater",
            "ver": "0.19.4"
          }
        },
        {
          "name": "patty",
          "str": ">= 0.3.3",
          "ver": {
            "kind": "verEqLater",
            "ver": "0.3.3"
          }
        }
      ],
      "bin": [],
      "binDir": "",
      "srcDir": "src",
      "backend": "c",
      "ref": "refs/tags/v0.1.0",
      "rev": "885079bf1a37d21a07bb2b472b295ca74e6b0df6"
    },
    "refs/tags/v0.2.0": {
      "name": "nimly",
      "version": "0.2.0",
      "author": "Lolo Iccl",
      "desc": "A lexer generator and parser generator package work in Nim.",
      "license": "GPL-3.0",
      "skipDirs": [],
      "skipFiles": [],
      "skipExt": [],
      "installDirs": [],
      "installFiles": [],
      "installExt": [],
      "requires": [
        {
          "name": "nim",
          "str": ">= 0.19.4",
          "ver": {
            "kind": "verEqLater",
            "ver": "0.19.4"
          }
        },
        {
          "name": "patty",
          "str": ">= 0.3.3",
          "ver": {
            "kind": "verEqLater",
            "ver": "0.3.3"
          }
        }
      ],
      "bin": [],
      "binDir": "",
      "srcDir": "src",
      "backend": "c",
      "ref": "refs/tags/v0.2.0",
      "rev": "60de20bc2db73fe0860e202289c0df4f4fd0f033"
    },
    "refs/tags/v0.2.1": {
      "name": "nimly",
      "version": "0.2.1",
      "author": "Lolo Iccl",
      "desc": "A lexer generator and parser generator package work in Nim.",
      "license": "GPL-3.0",
      "skipDirs": [],
      "skipFiles": [],
      "skipExt": [],
      "installDirs": [],
      "installFiles": [],
      "installExt": [],
      "requires": [
        {
          "name": "nim",
          "str": ">= 0.19.4",
          "ver": {
            "kind": "verEqLater",
            "ver": "0.19.4"
          }
        },
        {
          "name": "patty",
          "str": ">= 0.3.3",
          "ver": {
            "kind": "verEqLater",
            "ver": "0.3.3"
          }
        }
      ],
      "bin": [],
      "binDir": "",
      "srcDir": "src",
      "backend": "c",
      "ref": "refs/tags/v0.2.1",
      "rev": "1128e18dbcb268d4f78450fbbc67870c8bff014a"
    },
    "refs/tags/v0.3.0": {
      "name": "nimly",
      "version": "0.3.0",
      "author": "Lolo Iccl",
      "desc": "A lexer generator and parser generator package work in Nim.",
      "license": "GPL-3.0",
      "skipDirs": [],
      "skipFiles": [],
      "skipExt": [],
      "installDirs": [],
      "installFiles": [],
      "installExt": [],
      "requires": [
        {
          "name": "nim",
          "str": ">= 0.20.0",
          "ver": {
            "kind": "verEqLater",
            "ver": "0.20.0"
          }
        },
        {
          "name": "patty",
          "str": ">= 0.3.3",
          "ver": {
            "kind": "verEqLater",
            "ver": "0.3.3"
          }
        }
      ],
      "bin": [],
      "binDir": "",
      "srcDir": "src",
      "backend": "c",
      "ref": "refs/tags/v0.3.0",
      "rev": "4123204149f6a79f62d29182cd8af2feb06efe59"
    },
    "refs/tags/v0.4.0": {
      "name": "nimly",
      "version": "0.4.0",
      "author": "Lolo Iccl",
      "desc": "A lexer generator and parser generator package work in Nim.",
      "license": "GPL-3.0",
      "skipDirs": [],
      "skipFiles": [],
      "skipExt": [],
      "installDirs": [],
      "installFiles": [],
      "installExt": [],
      "requires": [
        {
          "name": "nim",
          "str": ">= 1.0.0",
          "ver": {
            "kind": "verEqLater",
            "ver": "1.0.0"
          }
        },
        {
          "name": "patty",
          "str": ">= 0.3.3",
          "ver": {
            "kind": "verEqLater",
            "ver": "0.3.3"
          }
        }
      ],
      "bin": [],
      "binDir": "",
      "srcDir": "src",
      "backend": "c",
      "ref": "refs/tags/v0.4.0",
      "rev": "3ffcb368e6f7d8119adb263cfe70b30502f6ac82"
    },
    "refs/tags/v0.4.1": {
      "name": "nimly",
      "version": "0.4.1",
      "author": "Lolo Iccl",
      "desc": "A lexer generator and parser generator package work in Nim.",
      "license": "GPL-3.0",
      "skipDirs": [],
      "skipFiles": [],
      "skipExt": [],
      "installDirs": [],
      "installFiles": [],
      "installExt": [],
      "requires": [
        {
          "name": "nim",
          "str": ">= 1.0.0",
          "ver": {
            "kind": "verEqLater",
            "ver": "1.0.0"
          }
        },
        {
          "name": "patty",
          "str": ">= 0.3.3",
          "ver": {
            "kind": "verEqLater",
            "ver": "0.3.3"
          }
        }
      ],
      "bin": [],
      "binDir": "",
      "srcDir": "src",
      "backend": "c",
      "ref": "refs/tags/v0.4.1",
      "rev": "20c683c4f638dd7839e4344e7fe68cefb63cc85e"
    },
    "refs/tags/v0.4.2": {
      "name": "nimly",
      "version": "0.4.2",
      "author": "Lolo Iccl",
      "desc": "Lexer Generator and Parser Generator as a library in Nim.",
      "license": "GPL-3.0",
      "skipDirs": [],
      "skipFiles": [],
      "skipExt": [],
      "installDirs": [],
      "installFiles": [],
      "installExt": [],
      "requires": [
        {
          "name": "nim",
          "str": ">= 1.0.0",
          "ver": {
            "kind": "verEqLater",
            "ver": "1.0.0"
          }
        },
        {
          "name": "patty",
          "str": ">= 0.3.3",
          "ver": {
            "kind": "verEqLater",
            "ver": "0.3.3"
          }
        }
      ],
      "bin": [],
      "binDir": "",
      "srcDir": "src",
      "backend": "c",
      "ref": "refs/tags/v0.4.2",
      "rev": "2d5e2623534076a5dc8acedf334b14625db2e986"
    },
    "refs/tags/v0.5.0": {
      "name": "nimly",
      "version": "0.5.0",
      "author": "Lolo Iccl",
      "desc": "Lexer Generator and Parser Generator as a library in Nim.",
      "license": "GPL-3.0",
      "skipDirs": [],
      "skipFiles": [],
      "skipExt": [],
      "installDirs": [],
      "installFiles": [],
      "installExt": [],
      "requires": [
        {
          "name": "nim",
          "str": ">= 1.0.0",
          "ver": {
            "kind": "verEqLater",
            "ver": "1.0.0"
          }
        },
        {
          "name": "patty",
          "str": ">= 0.3.3",
          "ver": {
            "kind": "verEqLater",
            "ver": "0.3.3"
          }
        }
      ],
      "bin": [],
      "binDir": "",
      "srcDir": "src",
      "backend": "c",
      "ref": "refs/tags/v0.5.0",
      "rev": "87e603f3e9c41f8dcb3c300869325af16e888834"
    },
    "refs/tags/v0.5.1": {
      "name": "nimly",
      "version": "0.5.1",
      "author": "Lolo Iccl",
      "desc": "Lexer Generator and Parser Generator as a library in Nim.",
      "license": "GPL-3.0",
      "skipDirs": [],
      "skipFiles": [],
      "skipExt": [],
      "installDirs": [],
      "installFiles": [],
      "installExt": [],
      "requires": [
        {
          "name": "nim",
          "str": ">= 1.0.0",
          "ver": {
            "kind": "verEqLater",
            "ver": "1.0.0"
          }
        },
        {
          "name": "patty",
          "str": ">= 0.3.3",
          "ver": {
            "kind": "verEqLater",
            "ver": "0.3.3"
          }
        }
      ],
      "bin": [],
      "binDir": "",
      "srcDir": "src",
      "backend": "c",
      "ref": "refs/tags/v0.5.1",
      "rev": "4cc3ada51e5b69c6e33af316ead6c7099f2d7931"
    },
    "refs/tags/v0.6.0": {
      "name": "nimly",
      "version": "0.6.0",
      "author": "loloicci",
      "desc": "Lexer Generator and Parser Generator as a library in Nim.",
      "license": "MIT",
      "skipDirs": [],
      "skipFiles": [],
      "skipExt": [],
      "installDirs": [],
      "installFiles": [],
      "installExt": [],
      "requires": [
        {
          "name": "nim",
          "str": ">= 1.0.0",
          "ver": {
            "kind": "verEqLater",
            "ver": "1.0.0"
          }
        },
        {
          "name": "patty",
          "str": ">= 0.3.3",
          "ver": {
            "kind": "verEqLater",
            "ver": "0.3.3"
          }
        }
      ],
      "bin": [],
      "binDir": "",
      "srcDir": "src",
      "backend": "c",
      "ref": "refs/tags/v0.6.0",
      "rev": "a39beb7dc969b308e8737ff9efdc9fad7ad9c3ed"
    },
    "refs/tags/v0.6.1": {
      "name": "nimly",
      "version": "0.6.1",
      "author": "loloicci",
      "desc": "Lexer Generator and Parser Generator as a library in Nim.",
      "license": "MIT",
      "skipDirs": [],
      "skipFiles": [],
      "skipExt": [],
      "installDirs": [],
      "installFiles": [],
      "installExt": [],
      "requires": [
        {
          "name": "nim",
          "str": ">= 1.0.0",
          "ver": {
            "kind": "verEqLater",
            "ver": "1.0.0"
          }
        },
        {
          "name": "patty",
          "str": ">= 0.3.3",
          "ver": {
            "kind": "verEqLater",
            "ver": "0.3.3"
          }
        }
      ],
      "bin": [],
      "binDir": "",
      "srcDir": "src",
      "backend": "c",
      "ref": "refs/tags/v0.6.1",
      "rev": "38cfaebe00199a8622d527b7dd67b3e6a168cfe2"
    },
    "refs/tags/v0.7.0": {
      "name": "nimly",
      "version": "0.7.0",
      "author": "loloicci",
      "desc": "Lexer Generator and Parser Generator as a library in Nim.",
      "license": "MIT",
      "skipDirs": [],
      "skipFiles": [],
      "skipExt": [],
      "installDirs": [],
      "installFiles": [],
      "installExt": [],
      "requires": [
        {
          "name": "nim",
          "str": ">= 1.4.0",
          "ver": {
            "kind": "verEqLater",
            "ver": "1.4.0"
          }
        },
        {
          "name": "patty",
          "str": ">= 0.3.3",
          "ver": {
            "kind": "verEqLater",
            "ver": "0.3.3"
          }
        }
      ],
      "bin": [],
      "binDir": "",
      "srcDir": "src",
      "backend": "c",
      "ref": "refs/tags/v0.7.0",
      "rev": "fa3a01ed8d51d0381a447a20c84459b664a13d1c"
    }
  }
}