{
  "name": "nimcorpora",
  "url": "https://github.com/neroist/nimcorpora",
  "method": "git",
  "tags": [
    "corpora"
  ],
  "description": "A Nim interface for Darius Kazemi's Corpora Project",
  "license": "0BSD",
  "web": "https://github.com/neroist/nimcorpora",
  "doc": "https://neroist.github.io/nimcorpora/nimcorpora.html",
  "refs": {
    "HEAD": {
      "name": "nimcorpora",
      "version": "0.1.1",
      "author": "Jasmine",
      "desc": "A Nim interface for Darius Kazemi's Corpora Project.",
      "license": "GPL-3.0-only",
      "skipDirs": [
        "examples",
        "docs"
      ],
      "skipFiles": [],
      "skipExt": [],
      "installDirs": [],
      "installFiles": [],
      "installExt": [],
      "requires": [
        {
          "name": "nim",
          "str": ">= 1.4.0",
          "ver": {
            "kind": "verEqLater",
            "ver": "1.4.0"
          }
        },
        {
          "name": "zippy",
          "str": "any version",
          "ver": {
            "kind": "verAny"
          }
        },
        {
          "name": "fab",
          "str": "any version",
          "ver": {
            "kind": "verAny"
          }
        }
      ],
      "bin": [],
      "binDir": "",
      "srcDir": "src",
      "backend": "c",
      "ref": "HEAD",
      "rev": "43f0edf3637ab6817a2f9621fcb5ec7523d46769"
    },
    "refs/heads/main": {
      "name": "nimcorpora",
      "version": "0.1.1",
      "author": "Jasmine",
      "desc": "A Nim interface for Darius Kazemi's Corpora Project.",
      "license": "GPL-3.0-only",
      "skipDirs": [
        "examples",
        "docs"
      ],
      "skipFiles": [],
      "skipExt": [],
      "installDirs": [],
      "installFiles": [],
      "installExt": [],
      "requires": [
        {
          "name": "nim",
          "str": ">= 1.4.0",
          "ver": {
            "kind": "verEqLater",
            "ver": "1.4.0"
          }
        },
        {
          "name": "zippy",
          "str": "any version",
          "ver": {
            "kind": "verAny"
          }
        },
        {
          "name": "fab",
          "str": "any version",
          "ver": {
            "kind": "verAny"
          }
        }
      ],
      "bin": [],
      "binDir": "",
      "srcDir": "src",
      "backend": "c",
      "ref": "refs/heads/main",
      "rev": "43f0edf3637ab6817a2f9621fcb5ec7523d46769"
    },
    "refs/tags/0.1.0": {
      "name": "nimcorpora",
      "version": "0.1.0",
      "author": "Jasmine",
      "desc": "A Nim interface for Darius Kazemi's Corpora Project.",
      "license": "GPL-3.0-only",
      "skipDirs": [
        "examples",
        "docs"
      ],
      "skipFiles": [],
      "skipExt": [],
      "installDirs": [],
      "installFiles": [],
      "installExt": [],
      "requires": [
        {
          "name": "nim",
          "str": ">= 1.6.10",
          "ver": {
            "kind": "verEqLater",
            "ver": "1.6.10"
          }
        },
        {
          "name": "zippy",
          "str": "any version",
          "ver": {
            "kind": "verAny"
          }
        },
        {
          "name": "fab",
          "str": "any version",
          "ver": {
            "kind": "verAny"
          }
        }
      ],
      "bin": [],
      "binDir": "",
      "srcDir": "src",
      "backend": "c",
      "ref": "refs/tags/0.1.0",
      "rev": "1a23ebfa9b2e580638d8fa2b96db6a92111a04f3"
    },
    "refs/tags/0.1.1": {
      "name": "nimcorpora",
      "version": "0.1.1",
      "author": "Jasmine",
      "desc": "A Nim interface for Darius Kazemi's Corpora Project.",
      "license": "GPL-3.0-only",
      "skipDirs": [
        "examples",
        "docs"
      ],
      "skipFiles": [],
      "skipExt": [],
      "installDirs": [],
      "installFiles": [],
      "installExt": [],
      "requires": [
        {
          "name": "nim",
          "str": ">= 1.4.0",
          "ver": {
            "kind": "verEqLater",
            "ver": "1.4.0"
          }
        },
        {
          "name": "zippy",
          "str": "any version",
          "ver": {
            "kind": "verAny"
          }
        },
        {
          "name": "fab",
          "str": "any version",
          "ver": {
            "kind": "verAny"
          }
        }
      ],
      "bin": [],
      "binDir": "",
      "srcDir": "src",
      "backend": "c",
      "ref": "refs/tags/0.1.1",
      "rev": "118e340c6fa95e816e702283620d46f396d3d8a7"
    }
  },
  "cudf": {
    "name": "nimcorpora",
    "version": {
      "1000": "refs/tags/0.1.0",
      "1001": "refs/tags/0.1.1"
    }
  }
}