{
  "name": "zxcvbnim",
  "url": "https://github.com/jiiihpeeh/zxcvbnim",
  "method": "git",
  "tags": [
    "zxcvbn",
    "clone"
  ],
  "description": "A zxcvbn clone for Nim. Written in Nim",
  "license": "MIT",
  "web": "https://github.com/jiiihpeeh/zxcvbnim",
  "refs": {
    "HEAD": {
      "name": "zxcvbnim",
      "version": "0.3.0",
      "author": "juujaa",
      "desc": "A zxcvbn clone for Nim. Written in Nim",
      "license": "MIT",
      "skipDirs": [],
      "skipFiles": [],
      "skipExt": [],
      "installDirs": [],
      "installFiles": [],
      "installExt": [],
      "requires": [
        {
          "name": "nim",
          "str": ">= 1.4.8",
          "ver": {
            "kind": "verEqLater",
            "ver": "1.4.8"
          }
        },
        {
          "name": "jsony",
          "str": "any version",
          "ver": {
            "kind": "verAny"
          }
        },
        {
          "name": "supersnappy",
          "str": "any version",
          "ver": {
            "kind": "verAny"
          }
        }
      ],
      "bin": [],
      "binDir": "",
      "srcDir": "src",
      "backend": "c",
      "ref": "HEAD",
      "rev": "e6223187af2bdea9a80d12f1c86e9cfdd0077989"
    },
    "refs/heads/jiiihpeeh-main-patch-66286": {
      "name": "zxcvbnim",
      "version": "0.3.0",
      "author": "juujaa",
      "desc": "A zxcvbn clone for Nim",
      "license": "MIT",
      "skipDirs": [],
      "skipFiles": [],
      "skipExt": [],
      "installDirs": [],
      "installFiles": [],
      "installExt": [],
      "requires": [
        {
          "name": "nim",
          "str": ">= 1.4.8",
          "ver": {
            "kind": "verEqLater",
            "ver": "1.4.8"
          }
        },
        {
          "name": "jsony",
          "str": "any version",
          "ver": {
            "kind": "verAny"
          }
        },
        {
          "name": "supersnappy",
          "str": "any version",
          "ver": {
            "kind": "verAny"
          }
        }
      ],
      "bin": [],
      "binDir": "",
      "srcDir": "src",
      "backend": "c",
      "ref": "refs/heads/jiiihpeeh-main-patch-66286",
      "rev": "949e894f077b3fb34b1bf638ff528478e4665234"
    },
    "refs/heads/main": {
      "name": "zxcvbnim",
      "version": "0.3.0",
      "author": "juujaa",
      "desc": "A zxcvbn clone for Nim. Written in Nim",
      "license": "MIT",
      "skipDirs": [],
      "skipFiles": [],
      "skipExt": [],
      "installDirs": [],
      "installFiles": [],
      "installExt": [],
      "requires": [
        {
          "name": "nim",
          "str": ">= 1.4.8",
          "ver": {
            "kind": "verEqLater",
            "ver": "1.4.8"
          }
        },
        {
          "name": "jsony",
          "str": "any version",
          "ver": {
            "kind": "verAny"
          }
        },
        {
          "name": "supersnappy",
          "str": "any version",
          "ver": {
            "kind": "verAny"
          }
        }
      ],
      "bin": [],
      "binDir": "",
      "srcDir": "src",
      "backend": "c",
      "ref": "refs/heads/main",
      "rev": "e6223187af2bdea9a80d12f1c86e9cfdd0077989"
    }
  }
}