{
  "name": "findxml",
  "version": "0.1.0",
  "author": "Thiago Ferreira",
  "desc": "XML search easy as JS DOM API",
  "license": "MIT",
  "skipDirs": [],
  "skipFiles": [],
  "skipExt": [],
  "installDirs": [],
  "installFiles": [],
  "installExt": [],
  "requires": [
    {
      "name": "nim",
      "str": ">= 1.0.0",
      "ver": {
        "kind": "verEqLater",
        "ver": "1.0.0"
      }
    }
  ],
  "bin": [],
  "binDir": "",
  "srcDir": "src",
  "backend": "c",
  "ref": "refs/heads/master"
}